Metadata-Version: 2.1
Name: buzzsprout
Version: 0.22
Summary: Buzzsprout Podcasts Python class
Home-page: https://github.com/Harrtron/buzzsprout-python
Author: Harley Thorne
Author-email: harleyjthorne@gmail.com
License: MIT
Platform: UNKNOWN
